[
  {
    "id":1,
    "name": "Drone Videography",
    "description": "At Kapture Design Studio, we redefine brand storytelling through the lens of the sky. Our Aerial Branding service takes your narrative to new heights, literally. Imagine capturing the essence of your brand not just from eye level, but from stunning bird's-eye views that unfold a unique perspective. With our state-of-the-art drones, we go beyond traditional storytelling. We navigate the skies, capturing awe-inspiring footage that seamlessly weaves your brand's story into the tapestry of the landscape. Whether it's showcasing expansive properties, dynamic events, or the sheer scale of your operations, our drone perspectives add a layer of visual richness that conventional methods simply can't match. From the graceful flow of landscapes to the intricate details of architectural marvels, our drones become the storytellers, translating the unique personality of your brand into visuals that resonate. It's not just about visuals; it's about creating an immersive experience that stays etched in the minds of your audience. Our Aerial Branding service is more than just capturing footage; it's about curating an aerial journey that aligns with your brand's identity. Elevate your narrative, soar above the ordinary, and let the sky become the canvas for your exceptional story.",
    "image": "/images/services/drone.jpg"
  },
  {
    "id":2,
    "name": "Drone Videography 3",
    "description": "At Kapture Design Studio, we redefine brand storytelling through the lens of the sky. Our Aerial Branding service takes your narrative to new heights, literally. Imagine capturing the essence of your brand not just from eye level, but from stunning bird's-eye views that unfold a unique perspective. With our state-of-the-art drones, we go beyond traditional storytelling. We navigate the skies, capturing awe-inspiring footage that seamlessly weaves your brand's story into the tapestry of the landscape. Whether it's showcasing expansive properties, dynamic events, or the sheer scale of your operations, our drone perspectives add a layer of visual richness that conventional methods simply can't match. From the graceful flow of landscapes to the intricate details of architectural marvels, our drones become the storytellers, translating the unique personality of your brand into visuals that resonate. It's not just about visuals; it's about creating an immersive experience that stays etched in the minds of your audience. Our Aerial Branding service is more than just capturing footage; it's about curating an aerial journey that aligns with your brand's identity. Elevate your narrative, soar above the ordinary, and let the sky become the canvas for your exceptional story.",
    "image": "/images/services/drone.jpg"
  }
]